<?xml version="1.0" encoding="utf-8"?>
<Entity parent="template_structure_civic">
  <AlertRaiser>
    <List datatype="tokens">FemaleCitizen</List>
    <RaiseAlertRange>120</RaiseAlertRange>
    <EndOfAlertRange>180</EndOfAlertRange>
    <SearchRange>100</SearchRange>
  </AlertRaiser>
  <Attack>
    <Ranged>
      <AttackName>Stone</AttackName>
      <Damage>
        <Hack>0.0</Hack>
        <Pierce>71.0</Pierce>
        <Crush>0.0</Crush>
      </Damage>
      <MaxRange>80</MaxRange>
      <MinRange>30</MinRange>
      <ElevationBonus>15</ElevationBonus>
      <PrepareTime>640</PrepareTime>
      <RepeatTime>4000</RepeatTime>
      <Projectile>
        <Speed>140</Speed>
        <Spread>6</Spread>
        <Gravity>9.81</Gravity>
        <FriendlyFire>false</FriendlyFire>
        <LaunchPoint y="3"/>
        <ActorName>props/units/weapons/slingrock</ActorName>
        <ImpactActorName>props/units/weapons/slingrock.xml</ImpactActorName>
        <ImpactAnimationLifetime>0.3</ImpactAnimationLifetime>
      </Projectile>
      <PreferredClasses datatype="tokens">Human !Organic</PreferredClasses>
    </Ranged>
  </Attack>
  <BuildingAI>
    <DefaultArrowCount>3</DefaultArrowCount>
    <GarrisonArrowMultiplier>1</GarrisonArrowMultiplier>
    <GarrisonArrowClasses>Soldier</GarrisonArrowClasses>
  </BuildingAI>
  <BuildRestrictions>
    <Territory>own neutral</Territory>
    <Category>CivilCentre</Category>
    <Distance>
      <FromClass>CivilCentre</FromClass>
      <MinDistance>200</MinDistance>
    </Distance>
  </BuildRestrictions>
  <Capturable>
    <CapturePoints>2500</CapturePoints>
    <RegenRate>5.0</RegenRate>
  </Capturable>
  <Cost>
    <BuildTime>500</BuildTime>
    <Resources>
      <wood>500</wood>
      <stone>500</stone>
      <metal>500</metal>
    </Resources>
  </Cost>
  <Footprint>
    <Square width="32.0" depth="32.0"/>
    <Height>8.0</Height>
  </Footprint>
  <GarrisonHolder>
    <Max>20</Max>
    <EjectHealth>0.1</EjectHealth>
    <EjectClassesOnDestroy datatype="tokens">Unit</EjectClassesOnDestroy>
    <List datatype="tokens">Support Infantry Cavalry</List>
    <BuffHeal>1</BuffHeal>
    <LoadingRange>1</LoadingRange>
  </GarrisonHolder>
  <Health>
    <Max>3000</Max>
    <SpawnEntityOnDeath>decay|rubble/rubble_stone_6x6</SpawnEntityOnDeath>
  </Health>
  <Identity>
    <GenericName>Civic Center</GenericName>
    <SelectionGroupName>template_structure_civic_civil_centre</SelectionGroupName>
    <Tooltip>Build in own or neutral territory. Acquire large tracts of territory. Territory root. Train Citizens and research technologies. Garrison Soldiers for additional arrows.</Tooltip>
    <Classes datatype="tokens">CivCentre</Classes>
    <VisibleClasses datatype="tokens">Defensive CivilCentre</VisibleClasses>
    <Icon>structures/civic_center.png</Icon>
  </Identity>
  <Loot>
    <wood>100</wood>
    <stone>100</stone>
    <metal>100</metal>
  </Loot>
  <Obstruction>
    <Static width="30.0" depth="30.0"/>
  </Obstruction>
  <Population>
    <Bonus>20</Bonus>
  </Population>
  <ProductionQueue>
    <BatchTimeModifier>0.8</BatchTimeModifier>
    <Entities datatype="tokens">
      units/{civ}/support_female_citizen
    </Entities>
    <Technologies datatype="tokens">
      phase_town_{civ}
      phase_city_{civ}
      unlock_shared_los
      unlock_shared_dropsites
      unlock_spies
      spy_counter
      archery_tradition
      hoplite_tradition
      hellenistic_metropolis
    </Technologies>
  </ProductionQueue>
  <Resistance>
    <Entity>
      <Damage>
        <Hack op="add">5</Hack>
        <Pierce op="add">5</Pierce>
      </Damage>
    </Entity>
  </Resistance>
  <ResourceDropsite>
    <Types>food wood stone metal</Types>
    <Sharable>true</Sharable>
  </ResourceDropsite>
  <Sound>
    <SoundGroups>
      <select>interface/select/building/sel_civ_center.xml</select>
      <constructed>interface/complete/building/complete_civ_center.xml</constructed>
      <alert_raise>interface/alarm/alarm_alert_0.xml</alert_raise>
      <alert_end>interface/alarm/alarm_alert_1.xml</alert_end>
      <attack_ranged>attack/weapon/bow_attack.xml</attack_ranged>
      <attack_impact_ranged>attack/impact/arrow_impact.xml</attack_impact_ranged>
    </SoundGroups>
  </Sound>
  <TerritoryInfluence>
    <Root>true</Root>
    <Radius>140</Radius>
    <Weight>10000</Weight>
  </TerritoryInfluence>
  <Vision>
    <Range>90</Range>
  </Vision>
  <VisualActor>
    <FoundationActor>structures/fndn_8x8.xml</FoundationActor>
  </VisualActor>
  <Sound>
    <SoundGroups>
      <attack_ranged>attack/weapon/musket.xml</attack_ranged>
      <walk></walk>
      <run></run>
    </SoundGroups>
  </Sound>
</Entity>
